Metadata-Version: 2.1
Name: opiplayer
Version: 0.2.2
Summary: A music player package for Linux
Author: ViDat
Author-email: tiendatopip@gmail.com
